<?xml version="1.0" encoding="UTF-8" standalone="yes" ?>



<title>KYBO 3.0.0</TITLE>




<item>
<title><COLOR aqua>***Romance***</COLOR></title>
</item>



<item>
<title>Fifty Shades of Grey (2015)</title>
<link></link>
<thumbnail>http://cdni.condenast.co.uk/720x1080/d_f/Fifty-Shades-of-Grey-Film-t_720x1080.jpg</thumbnail>
<fanart>http://images6.fanpop.com/image/photos/33800000/fifty-shades-of-grey-fifty-shades-trilogy-33869300-1920-1200.jpg</fanart>
<info>Literature student Anastasia Steele's life changes forever when she meets handsome, yet tormented, billionaire Christian Grey.</info>
</item>

<item>
<title>Romeo and Juliet (2014)</title>
<link></link>
<thumbnail>http://ecx.images-amazon.com/images/I/51dsfF5JLXL.jpg</thumbnail>
<fanart>http://i.ytimg.com/vi/mu-lMzHSNNk/maxresdefault.jpg</fanart>
<info>Orlando Bloom and Condola Rashad take on the title characters in a modern adaptation of the timeless classic, Romeo and Juliet. This Broadway stage production is being broadcast in movie theaters.</info>
</item>

<item>
<title>Dirty Dancing (1987)</title>
<link></link>
<thumbnail>http://upload.wikimedia.org/wikipedia/en/0/00/Dirty_Dancing.jpg</thumbnail>
<fanart>http://upload.wikimedia.org/wikipedia/en/1/13/Dirty-dancing-coverx-large.jpg</fanart>
<info>Spending the summer in a holiday camp with her family, Frances "Baby" Houseman falls in love with the camp's dance instructor Johnny Castle.</info>
</item>

<item>
<title></title>
<link></link>
<thumbnail></thumbnail>
<fanart></fanart>
<info></info>
</item>

